slurmise/__about__.py
slurmise/__init__.py
slurmise/__main__.py
slurmise/api.py
slurmise/config.py
slurmise/job_data.py
slurmise/job_database.py
slurmise/parse_args.py
slurmise/slurm.py
slurmise/utils.py
slurmise/fit/__init__.py
slurmise/fit/poly_fit.py
slurmise/fit/resource_fit.py
slurmise/job_parse/file_parsers.py
slurmise/job_parse/job_specification.py
slurmise-0.0.3.dist-info/METADATA
slurmise-0.0.3.dist-info/WHEEL
slurmise-0.0.3.dist-info/entry_points.txt
slurmise-0.0.3.dist-info/licenses/LICENSE
slurmise-0.0.3.dist-info/RECORD
