Metadata-Version: 2.4
Name: slurmise
Version: 0.0.3
Summary: Simple slurm resource estimation
Project-URL: Documentation, https://github.com/PrincetonUniversity/slurmise#readme
Project-URL: Issues, https://github.com/PrincetonUniversity/slurmise/issues
Project-URL: Source, https://github.com/PrincetonUniversity/slurmise
Author-email: Troy Comi <tcomi@princeton.edu>, Ioannis Paraskevakos <iparask@princeton.edu>
License-Expression: MIT
License-File: LICENSE
Classifier: Development Status :: 4 - Beta
Classifier: Programming Language :: Python
Classifier: Programming Language :: Python :: 3.11
Classifier: Programming Language :: Python :: 3.12
Classifier: Programming Language :: Python :: Implementation :: CPython
Classifier: Programming Language :: Python :: Implementation :: PyPy
Requires-Python: >=3.11
Requires-Dist: click
Requires-Dist: h5py
Requires-Dist: joblib
Requires-Dist: numpy
Requires-Dist: pandas
Requires-Dist: regex
Requires-Dist: scikit-learn
Requires-Dist: sphinx
Requires-Dist: sphinx-rtd-theme
Provides-Extra: dev
Requires-Dist: coverage; extra == 'dev'
Requires-Dist: coveralls; extra == 'dev'
Requires-Dist: pytest; extra == 'dev'
Requires-Dist: pytest-cov; extra == 'dev'
Requires-Dist: pytest-random-order; extra == 'dev'
Requires-Dist: ruff; extra == 'dev'
